LICENSE
README.md
setup.py
HiveNetFileTransfer/__init__.py
HiveNetFileTransfer/exceptions.py
HiveNetFileTransfer/protocol.py
HiveNetFileTransfer/saver.py
HiveNetFileTransfer/transfer.py
HiveNetFileTransfer.egg-info/PKG-INFO
HiveNetFileTransfer.egg-info/SOURCES.txt
HiveNetFileTransfer.egg-info/dependency_links.txt
HiveNetFileTransfer.egg-info/not-zip-safe
HiveNetFileTransfer.egg-info/requires.txt
HiveNetFileTransfer.egg-info/top_level.txt
HiveNetFileTransfer/extend_protocol/__init__.py
HiveNetFileTransfer/extend_protocol/grpc.py