Metadata-Version: 2.1
Name: HiveNetFileTransfer
Version: 0.1.0
Summary: A file transfer processing framework.
Home-page: https://github.com/snakeclub/HiveNetAssemble/HiveNetFileTransfer
Author: 黎慧剑
Author-email: snakeclub@163.com
Maintainer: 黎慧剑
Maintainer-email: snakeclub@163.com
License: Mozilla Public License 2.0
Keywords: HiveNetAssemble HiveNetFileTransfer transfer development python lib
Platform: all
Classifier: Operating System :: OS Independent
Classifier: License :: OSI Approved :: Mozilla Public License 2.0 (MPL 2.0)
Classifier: Programming Language :: Python :: 3.6
Classifier: Topic :: Software Development :: Libraries
License-File: LICENSE
